image_processor_client/__init__.py
image_processor_client/client.py
image_processor_client/_http/__init__.py
image_processor_client/_http/exceptions.py
image_processor_client/_http/gateway.py
image_processor_client/_http/response.py
image_processor_client/_http/route.py
image_processor_client/_http/functions/__init__.py
image_processor_client/_http/functions/discord.py
image_processor_client/_http/functions/memes.py
image_processor_client/_http/functions/models.py
image_processor_client/image_methods/__init__.py
image_processor_client/image_methods/discord.py
image_processor_client/image_methods/memes.py
image_processor_client/utils/__init__.py
image_processor_client/utils/image.py
tests/__init__.py
tests/test_client.py
tests/test_methods.py
tests/utils.py
image_processor_client-2.1.6.dist-info/LICENSE
image_processor_client-2.1.6.dist-info/METADATA
image_processor_client-2.1.6.dist-info/WHEEL
image_processor_client-2.1.6.dist-info/top_level.txt
image_processor_client-2.1.6.dist-info/RECORD
