Metadata-Version: 2.1
Name: image-processor-client
Version: 2.1.6
Summary: Asynchronous python client for image-processor server.
Home-page: https://github.com/thec0sm0s/image-processor-client
Author: □ | The Cosmos
License: UNKNOWN
Platform: UNKNOWN
Classifier: Development Status :: 4 - Beta
Classifier: License :: OSI Approved :: MIT License
Classifier: Intended Audience :: Developers
Classifier: Natural Language :: English
Classifier: Operating System :: OS Independent
Classifier: Programming Language :: Python :: 3.6
Classifier: Programming Language :: Python :: 3.7
Classifier: Topic :: Software Development :: Libraries
Classifier: Topic :: Internet
Classifier: Topic :: Utilities
Requires-Dist: aiohttp
Provides-Extra: docs
Requires-Dist: sphinx (==1.8.3) ; extra == 'docs'
